apputils/terminal/__init__.py
apputils/terminal/colors.py
apputils/terminal/get_terminal_size.py
apputils_terminal-2.0.2.dist-info/LICENSE
apputils_terminal-2.0.2.dist-info/METADATA
apputils_terminal-2.0.2.dist-info/WHEEL
apputils_terminal-2.0.2.dist-info/top_level.txt
apputils_terminal-2.0.2.dist-info/zip-safe
apputils_terminal-2.0.2.dist-info/RECORD
